fugue/__init__.py
fugue/api.py
fugue/constants.py
fugue/dev.py
fugue/exceptions.py
fugue/plugins.py
fugue/py.typed
fugue/registry.py
fugue/_utils/__init__.py
fugue/_utils/display.py
fugue/_utils/exception.py
fugue/_utils/interfaceless.py
fugue/_utils/io.py
fugue/_utils/misc.py
fugue/_utils/registry.py
fugue/bag/__init__.py
fugue/bag/array_bag.py
fugue/bag/bag.py
fugue/collections/__init__.py
fugue/collections/partition.py
fugue/collections/sql.py
fugue/collections/yielded.py
fugue/column/__init__.py
fugue/column/expressions.py
fugue/column/functions.py
fugue/column/sql.py
fugue/dataframe/__init__.py
fugue/dataframe/api.py
fugue/dataframe/array_dataframe.py
fugue/dataframe/arrow_dataframe.py
fugue/dataframe/dataframe.py
fugue/dataframe/dataframe_iterable_dataframe.py
fugue/dataframe/dataframes.py
fugue/dataframe/function_wrapper.py
fugue/dataframe/iterable_dataframe.py
fugue/dataframe/pandas_dataframe.py
fugue/dataframe/utils.py
fugue/dataset/__init__.py
fugue/dataset/api.py
fugue/dataset/dataset.py
fugue/execution/__init__.py
fugue/execution/api.py
fugue/execution/execution_engine.py
fugue/execution/factory.py
fugue/execution/native_execution_engine.py
fugue/extensions/__init__.py
fugue/extensions/_utils.py
fugue/extensions/context.py
fugue/extensions/_builtins/__init__.py
fugue/extensions/_builtins/creators.py
fugue/extensions/_builtins/outputters.py
fugue/extensions/_builtins/processors.py
fugue/extensions/creator/__init__.py
fugue/extensions/creator/convert.py
fugue/extensions/creator/creator.py
fugue/extensions/outputter/__init__.py
fugue/extensions/outputter/convert.py
fugue/extensions/outputter/outputter.py
fugue/extensions/processor/__init__.py
fugue/extensions/processor/convert.py
fugue/extensions/processor/processor.py
fugue/extensions/transformer/__init__.py
fugue/extensions/transformer/constants.py
fugue/extensions/transformer/convert.py
fugue/extensions/transformer/transformer.py
fugue/rpc/__init__.py
fugue/rpc/base.py
fugue/rpc/flask.py
fugue-0.9.6.dist-info/licenses/LICENSE
fugue-0.9.6.dist-info/METADATA
fugue-0.9.6.dist-info/WHEEL
fugue-0.9.6.dist-info/entry_points.txt
fugue-0.9.6.dist-info/top_level.txt
fugue-0.9.6.dist-info/RECORD
